LICENSE
MANIFEST.in
pyproject.toml
python-copr.spec
requirements.txt
run_tests.sh
setup.py
copr/README.rst
copr/__init__.py
copr/exceptions.py
copr/util.py
copr.egg-info/PKG-INFO
copr.egg-info/SOURCES.txt
copr.egg-info/dependency_links.txt
copr.egg-info/not-zip-safe
copr.egg-info/requires.txt
copr.egg-info/top_level.txt
copr/test/__init__.py
copr/test/client_v3/__init__.py
copr/test/client_v3/test_auth.py
copr/test/client_v3/test_builds.py
copr/test/client_v3/test_general.py
copr/test/client_v3/test_helpers.py
copr/test/client_v3/test_packages.py
copr/test/client_v3/test_requests.py
copr/test/resources/build_config.200.json
copr/test/resources/build_details.200.json
copr/test/resources/copr_cli.conf
copr/test/resources/projects_list.200.json
copr/v3/__init__.py
copr/v3/client.py
copr/v3/exceptions.py
copr/v3/helpers.py
copr/v3/pagination.py
copr/v3/requests.py
copr/v3/auth/__init__.py
copr/v3/auth/base.py
copr/v3/auth/gssapi.py
copr/v3/auth/token.py
copr/v3/proxies/__init__.py
copr/v3/proxies/build.py
copr/v3/proxies/build_chroot.py
copr/v3/proxies/mock_chroot.py
copr/v3/proxies/monitor.py
copr/v3/proxies/package.py
copr/v3/proxies/project.py
copr/v3/proxies/project_chroot.py
copr/v3/proxies/webhook.py
docs/ClientV1.rst
docs/ClientV2.rst
docs/ClientV3.rst
docs/Makefile
docs/README.txt
docs/conf.py
docs/index.rst
docs/installation.rst
docs/client_v1/Examples.rst
docs/client_v2/errors.rst
docs/client_v2/initialization.rst
docs/client_v2/resources_usage.rst
docs/client_v2/resource_info/build.rst
docs/client_v2/resource_info/build_task.rst
docs/client_v2/resource_info/mock_chroot.rst
docs/client_v2/resource_info/project.rst
docs/client_v2/resource_info/project_chroot.rst
docs/client_v3/build_options.rst
docs/client_v3/client_initialization.rst
docs/client_v3/data_structures.rst
docs/client_v3/error_handling.rst
docs/client_v3/migration.rst
docs/client_v3/package_source_types.rst
docs/client_v3/pagination.rst
docs/client_v3/proxies.rst
docs/client_v3/utilities.rst
docs/client_v3/working_with_proxies_directly.rst