Metadata-Version: 2.4
Name: copr
Version: 2.5
Summary: Python client for copr service.
Home-page: https://github.com/fedora-copr/copr
Author: Valentin Gologuzov
Author-email: vgologuz@redhat.com
License: GPLv2+
Classifier: License :: OSI Approved :: GNU General Public License v2 or later (GPLv2+)
Classifier: Programming Language :: Python :: 2
Classifier: Programming Language :: Python :: 2.7
Classifier: Programming Language :: Python :: 3
Classifier: Programming Language :: Python :: 3.6
Classifier: Topic :: System :: Archiving :: Packaging
Classifier: Development Status :: 3 - Alpha
License-File: LICENSE
Requires-Dist: filelock
Requires-Dist: requests
Requires-Dist: requests-toolbelt
Requires-Dist: setuptools
Requires-Dist: munch
Dynamic: author
Dynamic: author-email
Dynamic: classifier
Dynamic: description
Dynamic: home-page
Dynamic: license
Dynamic: license-file
Dynamic: requires-dist
Dynamic: summary
